evm_fm/__init__.py
evm_fm/__main__.py
evm_fm/constants.py
evm_fm/refresh_environment_variables.py
evm_fm/utils.py
evm_fm/templates/evm_temp_launchd.plist
evm_fm_python-0.1.6.dist-info/LICENSE.txt
evm_fm_python-0.1.6.dist-info/METADATA
evm_fm_python-0.1.6.dist-info/WHEEL
evm_fm_python-0.1.6.dist-info/entry_points.txt
evm_fm_python-0.1.6.dist-info/top_level.txt
evm_fm_python-0.1.6.dist-info/RECORD
