Metadata-Version: 2.1
Name: evm-fm-python
Version: 0.1.6
Summary: Environment variable manager for Mac
Home-page: https://github.com/andrewdieken/evm-fm-python
Author: Andrew Dieken
Author-email: andrewrd@live.com
License: MIT
Keywords: aws,environment,variable,manager,mac
Platform: UNKNOWN
Classifier: Development Status :: 3 - Alpha
Classifier: Intended Audience :: Developers
Classifier: Topic :: Software Development :: Build Tools
Classifier: License :: OSI Approved :: MIT License
Classifier: Programming Language :: Python :: 3
Classifier: Programming Language :: Python :: 3.4
Classifier: Programming Language :: Python :: 3.5
Classifier: Programming Language :: Python :: 3.6
Classifier: Programming Language :: Python :: 3.7
Requires-Dist: toml (>=0.10.1)
Requires-Dist: ssm-parameter-store (==19.11.0)
